[
    {
        "title": "Tropicale Foods Recalls Certain Helados Mexico and La Michoacana Products Due to Undeclared Milk",
        "company_announce_dttm": "2025-07-25T04:00:00+00:00",
        "notification_dttm": "2025-07-26T17:00:00+00:00",
        "recall_reason": "Undeclared milk",
        "company_name": "Tropicale Foods",
        "brand_name": "La Michoacana, Helados Mexico",
        "product_description": "Ice cream products",
        "impacted_states": [
            "CA",
            "US"
        ],
        "agency": "FDA",
        "uid": "be8ddec7-0fef-4735-94a3-93d8107b632d",
        "recall_url": "http://www.fda.gov/safety/recalls-market-withdrawals-safety-alerts/tropicale-foods-recalls-certain-helados-mexico-and-la-michoacana-products-due-undeclared-milk",
        "notice_id_number": null,
        "recall_type": null,
        "risk_level": "Potentially High - Class I",
        "recall_classification": "Potentially Class I"
    }
]